<?xml version="1.0" encoding="UTF-8"?>
<objects serializationModel="Studio.02.02.00">
	<object class="AudioFile" id="{1E095974-5427-4D4A-A5FA-0D4BF1963C81}">
		<property name="assetPath">
			<value>voice/attack/female/vc_1_attack_left_flankF3.ogg</value>
		</property>
		<property name="frequencyInKHz">
			<value>44.0999985</value>
		</property>
		<property name="channelCount">
			<value>2</value>
		</property>
		<property name="length">
			<value>1.5940589569</value>
		</property>
		<relationship name="masterAssetFolder">
			<destination>{b6479c9e-7ccd-4767-8111-a7d2a8925708}</destination>
		</relationship>
	</object>
</objects>
