<?xml version="1.0" encoding="UTF-8"?>
<objects serializationModel="Studio.02.02.00">
	<object class="AudioFile" id="{604A8CAB-33F8-444D-9196-AF3DDF6D5223}">
		<property name="assetPath">
			<value>voice/self/male/vc_1_self_attacking_siege_tower1.ogg</value>
		</property>
		<property name="frequencyInKHz">
			<value>44.0999985</value>
		</property>
		<property name="channelCount">
			<value>2</value>
		</property>
		<property name="length">
			<value>3.0633106576</value>
		</property>
		<relationship name="masterAssetFolder">
			<destination>{b6479c9e-7ccd-4767-8111-a7d2a8925708}</destination>
		</relationship>
	</object>
</objects>
